Metadata-Version: 1.0
Name: MCP23XXX
Version: 0.0.3
Summary: CraftBeerPi Plugin
Home-page: UNKNOWN
Author: Lawrence Wagy
Author-email: lnwagy@gmail.com
License: UNKNOWN
Platform: UNKNOWN
